aiohttp_theme/__init__.py
aiohttp_theme/_version.py
aiohttp_theme/about.html
aiohttp_theme/donate.html
aiohttp_theme/layout.html
aiohttp_theme/navigation.html
aiohttp_theme/relations.html
aiohttp_theme/support.py
aiohttp_theme/theme.conf
aiohttp_theme/static/aiohttp.css_t
aiohttp_theme/static/custom.css
aiohttp_theme-0.1.6.dist-info/LICENSE
aiohttp_theme-0.1.6.dist-info/METADATA
aiohttp_theme-0.1.6.dist-info/WHEEL
aiohttp_theme-0.1.6.dist-info/entry_points.txt
aiohttp_theme-0.1.6.dist-info/top_level.txt
aiohttp_theme-0.1.6.dist-info/RECORD
